invocare/__init__.py
invocare/util.py
invocare-0.2.1.dist-info/DESCRIPTION.rst
invocare-0.2.1.dist-info/METADATA
invocare-0.2.1.dist-info/RECORD
invocare-0.2.1.dist-info/WHEEL
invocare-0.2.1.dist-info/metadata.json
invocare-0.2.1.dist-info/top_level.txt
