Metadata-Version: 2.0
Name: invocare
Version: 0.2.1
Summary: A namespace for invocations.
Home-page: https://github.com/jbronn/invocare
Author: Justin Bronn
Author-email: jbronn@gmail.com
License: Apache License 2.0
Download-URL: https://pypi.python.org/pypi/invocare/
Platform: UNKNOWN
Classifier: Development Status :: 4 - Beta
Classifier: Intended Audience :: Developers
Classifier: Intended Audience :: System Administrators
Classifier: License :: OSI Approved :: Apache Software License
Classifier: Programming Language :: Python
Classifier: Programming Language :: Python :: 2
Classifier: Programming Language :: Python :: 3
Requires-Dist: invoke (>=0.16.3,<1.0.0)
